{
    "id": "https://twitter.com/noreal_koma/status/1883825276666380545",
    "publishDate": "2025-01-27T10:32:00+00:00",
    "text": [
        "では",
        "睾丸を破壊します",
        "!!?"
    ],
    "reading": [
        "では",
        "こうがんをはかいします",
        ""
    ],
    "tag": [
        "巨乳",
        "カードゲーム"
    ],
    "series": [],
    "characters": [],
    "relatedLinks": [
        {
            "type": "SUZURI",
            "title": "引いたカードに書かれた人物の内臓を破壊するゲーム",
            "url": "https://suzuri.jp/noreal_koma/designs/17268462"
        },
        {
            "type": "LINEスタンプ",
            "title": "存在しない漫画のLINEスタンプ 第２弾",
            "url": "https://store.line.me/stickershop/product/30111083/ja"
        },
        {
            "type": "Instagram",
            "title": "Instagram",
            "url": "https://www.instagram.com/noreal_koma/p/DFVMeUoSJ85/"
        }
    ]
}
