{
    "id": "https://x.com/noreal_koma/status/1975871794092384305",
    "embed": "https://twitter.com/noreal_koma/status/1975871794092384305",
    "publishDate": "2025-10-08T10:32:00+00:00",
    "text": [
        "な、何を言って……",
        "まだ分からねーのか!?",
        "お前は売られたってことだよ!!",
        "ぎゃははは!!"
    ],
    "reading": [
        "ななにをいって",
        "まだわからねーのか",
        "おまえはうられたってことだよ",
        "ぎゃははは"
    ],
    "tag": [
        "眼鏡",
        "メカクレ",
        "ピアス"
    ],
    "series": [],
    "characters": [],
    "relatedLinks": []
}
