{
    "id": "https://x.com/noreal_koma/status/1997615065789517914",
    "embed": "https://twitter.com/noreal_koma/status/1997615065789517914",
    "publishDate": "2025-12-07T10:32:00+00:00",
    "text": [
        "興味無い。",
        "俺は強者と戦えればそれでいい。",
        "ランクB 98位 \"斬鬼神\" ユリン＝グレゴリア"
    ],
    "reading": [
        "きょうみない",
        "おれはきょうしゃとたたかえればそれでいい",
        "らんくびーきゅうじゅうはちいざんきしんゆりんぐれごりあ"
    ],
    "tag": [
        "三つ編み",
        "スーツ",
        "ネクタイ",
        "片目隠れ",
        "傷跡"
    ],
    "series": [],
    "characters": [],
    "relatedLinks": []
}
