{
    "id": "https://x.com/noreal_koma/status/2060670554420412880",
    "embed": "https://twitter.com/noreal_koma/status/2060670554420412880",
    "publishDate": "2026-05-30T10:32:00+00:00",
    "text": [
        "与えられた異能(エクストラ)は「目が合った者を液状化させる力」",
        "だが塙は7歳の頃に病で眼球を摘出している",
        "そんな塙が異能を発動すべく取った行動は――"
    ],
    "reading": [
        "あたえられたえくすとらはめがあったものをえきじょうかさせるちから",
        "だがはなわはななさいのころにやまいでがんきゅうをてきしゅつしている",
        "そんなはなわがいのうをはつどうすべくとったこうどうは"
    ],
    "tag": [
        "三つ編み",
        "ネクタイ",
        "流血",
        "能力"
    ],
    "series": [],
    "characters": [],
    "relatedLinks": []
}
