{
    "id": "https://x.com/noreal_koma/status/1972610303176442156",
    "embed": "https://twitter.com/noreal_koma/status/1972610303176442156",
    "publishDate": "2025-09-29T10:32:00+00:00",
    "text": [
        "奏太!!お前からも何か言ってやれ……",
        "アホカス",
        "裏写り利用するな!!",
        "電子版どうすんだ"
    ],
    "reading": [
        "そうたおまえからもなにかいってやれ",
        "あほかす",
        "うらうつりりようするな",
        "でんしばんどうすんだ"
    ],
    "tag": [
        "眼鏡",
        "ジャージ",
        "ぱっつん",
        "裏写り"
    ],
    "series": [],
    "characters": [],
    "relatedLinks": []
}
