{
    "id": "https://x.com/noreal_koma/status/2016459234993426485",
    "embed": "https://twitter.com/noreal_koma/status/2016459234993426485",
    "publishDate": "2026-01-28T10:32:00+00:00",
    "text": [
        "寿命と引き換えに借金を帳消しにする能力だ",
        "商売にすりゃあここまでの繁盛ぶりにもなるわな",
        "…………"
    ],
    "reading": [
        "じゅみょうとひきかえにしゃっきんをちょうけしにするのうりょくだ",
        "しょうばいにすりゃあここまでのはんじょうぶりにもなるわな",
        ""
    ],
    "tag": [
        "スーツ",
        "ネクタイ",
        "巨乳"
    ],
    "series": [],
    "characters": [],
    "relatedLinks": []
}
